sim800l/__init__.py
sim800l/__version__.py
sim800l/sim800l.py
sim800l_gsm_module-1.0.1.dist-info/LICENSE
sim800l_gsm_module-1.0.1.dist-info/METADATA
sim800l_gsm_module-1.0.1.dist-info/WHEEL
sim800l_gsm_module-1.0.1.dist-info/top_level.txt
sim800l_gsm_module-1.0.1.dist-info/RECORD
