Metadata-Version: 2.1
Name: sim800l-gsm-module
Version: 1.0.1
Summary: Raspberry Pi SIM800L GSM module
Home-page: https://github.com/Ircama/raspberry-pi-sim800l-gsm-module
Author: Ircama
License: CC-BY-NC-SA-4.0
Keywords: Raspberry Pi SIM800L GSM module
Classifier: Operating System :: POSIX :: Linux
Classifier: License :: Other/Proprietary License
Classifier: Topic :: Communications
Classifier: Topic :: Software Development :: Libraries :: Python Modules
Classifier: Programming Language :: Python :: 3 :: Only
Classifier: Development Status :: 5 - Production/Stable
Classifier: Intended Audience :: Telecommunications Industry
Classifier: Intended Audience :: Developers
Requires-Python: >3.5
License-File: LICENSE
